[{"model": "auth.permission", "pk": 1, "fields": {"name": "Can use Structure mode", "content_type": 1, "codename": "use_structure"}}, {"model": "auth.permission", "pk": 2, "fields": {"name": "Can change page", "content_type": 2, "codename": "change_page"}}, {"model": "auth.permission", "pk": 3, "fields": {"name": "Can add log entry", "content_type": 3, "codename": "add_logentry"}}, {"model": "auth.permission", "pk": 4, "fields": {"name": "Can change log entry", "content_type": 3, "codename": "change_logentry"}}, {"model": "auth.permission", "pk": 5, "fields": {"name": "Can delete log entry", "content_type": 3, "codename": "delete_logentry"}}, {"model": "auth.permission", "pk": 6, "fields": {"name": "Can view log entry", "content_type": 3, "codename": "view_logentry"}}, {"model": "auth.permission", "pk": 7, "fields": {"name": "Can add permission", "content_type": 4, "codename": "add_permission"}}, {"model": "auth.permission", "pk": 8, "fields": {"name": "Can change permission", "content_type": 4, "codename": "change_permission"}}, {"model": "auth.permission", "pk": 9, "fields": {"name": "Can delete permission", "content_type": 4, "codename": "delete_permission"}}, {"model": "auth.permission", "pk": 10, "fields": {"name": "Can view permission", "content_type": 4, "codename": "view_permission"}}, {"model": "auth.permission", "pk": 11, "fields": {"name": "Can add group", "content_type": 5, "codename": "add_group"}}, {"model": "auth.permission", "pk": 12, "fields": {"name": "Can change group", "content_type": 5, "codename": "change_group"}}, {"model": "auth.permission", "pk": 13, "fields": {"name": "Can delete group", "content_type": 5, "codename": "delete_group"}}, {"model": "auth.permission", "pk": 14, "fields": {"name": "Can view group", "content_type": 5, "codename": "view_group"}}, {"model": "auth.permission", "pk": 15, "fields": {"name": "Can add user", "content_type": 6, "codename": "add_user"}}, {"model": "auth.permission", "pk": 16, "fields": {"name": "Can change user", "content_type": 6, "codename": "change_user"}}, {"model": "auth.permission", "pk": 17, "fields": {"name": "Can delete user", "content_type": 6, "codename": "delete_user"}}, {"model": "auth.permission", "pk": 18, "fields": {"name": "Can view user", "content_type": 6, "codename": "view_user"}}, {"model": "auth.permission", "pk": 19, "fields": {"name": "Can add content type", "content_type": 7, "codename": "add_contenttype"}}, {"model": "auth.permission", "pk": 20, "fields": {"name": "Can change content type", "content_type": 7, "codename": "change_contenttype"}}, {"model": "auth.permission", "pk": 21, "fields": {"name": "Can delete content type", "content_type": 7, "codename": "delete_contenttype"}}, {"model": "auth.permission", "pk": 22, "fields": {"name": "Can view content type", "content_type": 7, "codename": "view_contenttype"}}, {"model": "auth.permission", "pk": 23, "fields": {"name": "Can add session", "content_type": 8, "codename": "add_session"}}, {"model": "auth.permission", "pk": 24, "fields": {"name": "Can change session", "content_type": 8, "codename": "change_session"}}, {"model": "auth.permission", "pk": 25, "fields": {"name": "Can delete session", "content_type": 8, "codename": "delete_session"}}, {"model": "auth.permission", "pk": 26, "fields": {"name": "Can view session", "content_type": 8, "codename": "view_session"}}, {"model": "auth.permission", "pk": 27, "fields": {"name": "Can add site", "content_type": 9, "codename": "add_site"}}, {"model": "auth.permission", "pk": 28, "fields": {"name": "Can change site", "content_type": 9, "codename": "change_site"}}, {"model": "auth.permission", "pk": 29, "fields": {"name": "Can delete site", "content_type": 9, "codename": "delete_site"}}, {"model": "auth.permission", "pk": 30, "fields": {"name": "Can view site", "content_type": 9, "codename": "view_site"}}, {"model": "auth.permission", "pk": 31, "fields": {"name": "Can add cms plugin", "content_type": 10, "codename": "add_cmsplugin"}}, {"model": "auth.permission", "pk": 32, "fields": {"name": "Can change cms plugin", "content_type": 10, "codename": "change_cmsplugin"}}, {"model": "auth.permission", "pk": 33, "fields": {"name": "Can delete cms plugin", "content_type": 10, "codename": "delete_cmsplugin"}}, {"model": "auth.permission", "pk": 34, "fields": {"name": "Can view cms plugin", "content_type": 10, "codename": "view_cmsplugin"}}, {"model": "auth.permission", "pk": 35, "fields": {"name": "Can add alias plugin model", "content_type": 11, "codename": "add_aliaspluginmodel"}}, {"model": "auth.permission", "pk": 36, "fields": {"name": "Can change alias plugin model", "content_type": 11, "codename": "change_aliaspluginmodel"}}, {"model": "auth.permission", "pk": 37, "fields": {"name": "Can delete alias plugin model", "content_type": 11, "codename": "delete_aliaspluginmodel"}}, {"model": "auth.permission", "pk": 38, "fields": {"name": "Can view alias plugin model", "content_type": 11, "codename": "view_aliaspluginmodel"}}, {"model": "auth.permission", "pk": 39, "fields": {"name": "Can add Page global permission", "content_type": 12, "codename": "add_globalpagepermission"}}, {"model": "auth.permission", "pk": 40, "fields": {"name": "Can change Page global permission", "content_type": 12, "codename": "change_globalpagepermission"}}, {"model": "auth.permission", "pk": 41, "fields": {"name": "Can delete Page global permission", "content_type": 12, "codename": "delete_globalpagepermission"}}, {"model": "auth.permission", "pk": 42, "fields": {"name": "Can view Page global permission", "content_type": 12, "codename": "view_globalpagepermission"}}, {"model": "auth.permission", "pk": 43, "fields": {"name": "Can add page", "content_type": 2, "codename": "add_page"}}, {"model": "auth.permission", "pk": 44, "fields": {"name": "Can delete page", "content_type": 2, "codename": "delete_page"}}, {"model": "auth.permission", "pk": 45, "fields": {"name": "Can view page", "content_type": 2, "codename": "view_page"}}, {"model": "auth.permission", "pk": 46, "fields": {"name": "Can publish page", "content_type": 2, "codename": "publish_page"}}, {"model": "auth.permission", "pk": 47, "fields": {"name": "Can edit static placeholders", "content_type": 2, "codename": "edit_static_placeholder"}}, {"model": "auth.permission", "pk": 48, "fields": {"name": "Can add Page permission", "content_type": 13, "codename": "add_pagepermission"}}, {"model": "auth.permission", "pk": 49, "fields": {"name": "Can change Page permission", "content_type": 13, "codename": "change_pagepermission"}}, {"model": "auth.permission", "pk": 50, "fields": {"name": "Can delete Page permission", "content_type": 13, "codename": "delete_pagepermission"}}, {"model": "auth.permission", "pk": 51, "fields": {"name": "Can view Page permission", "content_type": 13, "codename": "view_pagepermission"}}, {"model": "auth.permission", "pk": 52, "fields": {"name": "Can add User (page)", "content_type": 14, "codename": "add_pageuser"}}, {"model": "auth.permission", "pk": 53, "fields": {"name": "Can change User (page)", "content_type": 14, "codename": "change_pageuser"}}, {"model": "auth.permission", "pk": 54, "fields": {"name": "Can delete User (page)", "content_type": 14, "codename": "delete_pageuser"}}, {"model": "auth.permission", "pk": 55, "fields": {"name": "Can view User (page)", "content_type": 14, "codename": "view_pageuser"}}, {"model": "auth.permission", "pk": 56, "fields": {"name": "Can add User group (page)", "content_type": 15, "codename": "add_pageusergroup"}}, {"model": "auth.permission", "pk": 57, "fields": {"name": "Can change User group (page)", "content_type": 15, "codename": "change_pageusergroup"}}, {"model": "auth.permission", "pk": 58, "fields": {"name": "Can delete User group (page)", "content_type": 15, "codename": "delete_pageusergroup"}}, {"model": "auth.permission", "pk": 59, "fields": {"name": "Can view User group (page)", "content_type": 15, "codename": "view_pageusergroup"}}, {"model": "auth.permission", "pk": 60, "fields": {"name": "Can add placeholder", "content_type": 1, "codename": "add_placeholder"}}, {"model": "auth.permission", "pk": 61, "fields": {"name": "Can change placeholder", "content_type": 1, "codename": "change_placeholder"}}, {"model": "auth.permission", "pk": 62, "fields": {"name": "Can delete placeholder", "content_type": 1, "codename": "delete_placeholder"}}, {"model": "auth.permission", "pk": 63, "fields": {"name": "Can view placeholder", "content_type": 1, "codename": "view_placeholder"}}, {"model": "auth.permission", "pk": 64, "fields": {"name": "Can add placeholder reference", "content_type": 16, "codename": "add_placeholderreference"}}, {"model": "auth.permission", "pk": 65, "fields": {"name": "Can change placeholder reference", "content_type": 16, "codename": "change_placeholderreference"}}, {"model": "auth.permission", "pk": 66, "fields": {"name": "Can delete placeholder reference", "content_type": 16, "codename": "delete_placeholderreference"}}, {"model": "auth.permission", "pk": 67, "fields": {"name": "Can view placeholder reference", "content_type": 16, "codename": "view_placeholderreference"}}, {"model": "auth.permission", "pk": 68, "fields": {"name": "Can add static placeholder", "content_type": 17, "codename": "add_staticplaceholder"}}, {"model": "auth.permission", "pk": 69, "fields": {"name": "Can change static placeholder", "content_type": 17, "codename": "change_staticplaceholder"}}, {"model": "auth.permission", "pk": 70, "fields": {"name": "Can delete static placeholder", "content_type": 17, "codename": "delete_staticplaceholder"}}, {"model": "auth.permission", "pk": 71, "fields": {"name": "Can view static placeholder", "content_type": 17, "codename": "view_staticplaceholder"}}, {"model": "auth.permission", "pk": 72, "fields": {"name": "Can add title", "content_type": 18, "codename": "add_title"}}, {"model": "auth.permission", "pk": 73, "fields": {"name": "Can change title", "content_type": 18, "codename": "change_title"}}, {"model": "auth.permission", "pk": 74, "fields": {"name": "Can delete title", "content_type": 18, "codename": "delete_title"}}, {"model": "auth.permission", "pk": 75, "fields": {"name": "Can view title", "content_type": 18, "codename": "view_title"}}, {"model": "auth.permission", "pk": 76, "fields": {"name": "Can add user setting", "content_type": 19, "codename": "add_usersettings"}}, {"model": "auth.permission", "pk": 77, "fields": {"name": "Can change user setting", "content_type": 19, "codename": "change_usersettings"}}, {"model": "auth.permission", "pk": 78, "fields": {"name": "Can delete user setting", "content_type": 19, "codename": "delete_usersettings"}}, {"model": "auth.permission", "pk": 79, "fields": {"name": "Can view user setting", "content_type": 19, "codename": "view_usersettings"}}, {"model": "auth.permission", "pk": 80, "fields": {"name": "Can add urlconf revision", "content_type": 20, "codename": "add_urlconfrevision"}}, {"model": "auth.permission", "pk": 81, "fields": {"name": "Can change urlconf revision", "content_type": 20, "codename": "change_urlconfrevision"}}, {"model": "auth.permission", "pk": 82, "fields": {"name": "Can delete urlconf revision", "content_type": 20, "codename": "delete_urlconfrevision"}}, {"model": "auth.permission", "pk": 83, "fields": {"name": "Can view urlconf revision", "content_type": 20, "codename": "view_urlconfrevision"}}, {"model": "auth.permission", "pk": 84, "fields": {"name": "Can add cache key", "content_type": 23, "codename": "add_cachekey"}}, {"model": "auth.permission", "pk": 85, "fields": {"name": "Can change cache key", "content_type": 23, "codename": "change_cachekey"}}, {"model": "auth.permission", "pk": 86, "fields": {"name": "Can delete cache key", "content_type": 23, "codename": "delete_cachekey"}}, {"model": "auth.permission", "pk": 87, "fields": {"name": "Can view cache key", "content_type": 23, "codename": "view_cachekey"}}, {"model": "auth.permission", "pk": 88, "fields": {"name": "Can add clipboard", "content_type": 24, "codename": "add_clipboard"}}, {"model": "auth.permission", "pk": 89, "fields": {"name": "Can change clipboard", "content_type": 24, "codename": "change_clipboard"}}, {"model": "auth.permission", "pk": 90, "fields": {"name": "Can delete clipboard", "content_type": 24, "codename": "delete_clipboard"}}, {"model": "auth.permission", "pk": 91, "fields": {"name": "Can view clipboard", "content_type": 24, "codename": "view_clipboard"}}, {"model": "auth.permission", "pk": 92, "fields": {"name": "Can add clipboard item", "content_type": 25, "codename": "add_clipboarditem"}}, {"model": "auth.permission", "pk": 93, "fields": {"name": "Can change clipboard item", "content_type": 25, "codename": "change_clipboarditem"}}, {"model": "auth.permission", "pk": 94, "fields": {"name": "Can delete clipboard item", "content_type": 25, "codename": "delete_clipboarditem"}}, {"model": "auth.permission", "pk": 95, "fields": {"name": "Can view clipboard item", "content_type": 25, "codename": "view_clipboarditem"}}, {"model": "auth.permission", "pk": 96, "fields": {"name": "Can add file", "content_type": 26, "codename": "add_file"}}, {"model": "auth.permission", "pk": 97, "fields": {"name": "Can change file", "content_type": 26, "codename": "change_file"}}, {"model": "auth.permission", "pk": 98, "fields": {"name": "Can delete file", "content_type": 26, "codename": "delete_file"}}, {"model": "auth.permission", "pk": 99, "fields": {"name": "Can view file", "content_type": 26, "codename": "view_file"}}, {"model": "auth.permission", "pk": 100, "fields": {"name": "Can add Folder", "content_type": 27, "codename": "add_folder"}}, {"model": "auth.permission", "pk": 101, "fields": {"name": "Can change Folder", "content_type": 27, "codename": "change_folder"}}, {"model": "auth.permission", "pk": 102, "fields": {"name": "Can delete Folder", "content_type": 27, "codename": "delete_folder"}}, {"model": "auth.permission", "pk": 103, "fields": {"name": "Can view Folder", "content_type": 27, "codename": "view_folder"}}, {"model": "auth.permission", "pk": 104, "fields": {"name": "Can use directory listing", "content_type": 27, "codename": "can_use_directory_listing"}}, {"model": "auth.permission", "pk": 105, "fields": {"name": "Can add folder permission", "content_type": 28, "codename": "add_folderpermission"}}, {"model": "auth.permission", "pk": 106, "fields": {"name": "Can change folder permission", "content_type": 28, "codename": "change_folderpermission"}}, {"model": "auth.permission", "pk": 107, "fields": {"name": "Can delete folder permission", "content_type": 28, "codename": "delete_folderpermission"}}, {"model": "auth.permission", "pk": 108, "fields": {"name": "Can view folder permission", "content_type": 28, "codename": "view_folderpermission"}}, {"model": "auth.permission", "pk": 109, "fields": {"name": "Can add image", "content_type": 29, "codename": "add_image"}}, {"model": "auth.permission", "pk": 110, "fields": {"name": "Can change image", "content_type": 29, "codename": "change_image"}}, {"model": "auth.permission", "pk": 111, "fields": {"name": "Can delete image", "content_type": 29, "codename": "delete_image"}}, {"model": "auth.permission", "pk": 112, "fields": {"name": "Can view image", "content_type": 29, "codename": "view_image"}}, {"model": "auth.permission", "pk": 113, "fields": {"name": "Can add thumbnail option", "content_type": 30, "codename": "add_thumbnailoption"}}, {"model": "auth.permission", "pk": 114, "fields": {"name": "Can change thumbnail option", "content_type": 30, "codename": "change_thumbnailoption"}}, {"model": "auth.permission", "pk": 115, "fields": {"name": "Can delete thumbnail option", "content_type": 30, "codename": "delete_thumbnailoption"}}, {"model": "auth.permission", "pk": 116, "fields": {"name": "Can view thumbnail option", "content_type": 30, "codename": "view_thumbnailoption"}}, {"model": "auth.permission", "pk": 117, "fields": {"name": "Can add source", "content_type": 31, "codename": "add_source"}}, {"model": "auth.permission", "pk": 118, "fields": {"name": "Can change source", "content_type": 31, "codename": "change_source"}}, {"model": "auth.permission", "pk": 119, "fields": {"name": "Can delete source", "content_type": 31, "codename": "delete_source"}}, {"model": "auth.permission", "pk": 120, "fields": {"name": "Can view source", "content_type": 31, "codename": "view_source"}}, {"model": "auth.permission", "pk": 121, "fields": {"name": "Can add thumbnail", "content_type": 32, "codename": "add_thumbnail"}}, {"model": "auth.permission", "pk": 122, "fields": {"name": "Can change thumbnail", "content_type": 32, "codename": "change_thumbnail"}}, {"model": "auth.permission", "pk": 123, "fields": {"name": "Can delete thumbnail", "content_type": 32, "codename": "delete_thumbnail"}}, {"model": "auth.permission", "pk": 124, "fields": {"name": "Can view thumbnail", "content_type": 32, "codename": "view_thumbnail"}}, {"model": "auth.permission", "pk": 125, "fields": {"name": "Can add thumbnail dimensions", "content_type": 33, "codename": "add_thumbnaildimensions"}}, {"model": "auth.permission", "pk": 126, "fields": {"name": "Can change thumbnail dimensions", "content_type": 33, "codename": "change_thumbnaildimensions"}}, {"model": "auth.permission", "pk": 127, "fields": {"name": "Can delete thumbnail dimensions", "content_type": 33, "codename": "delete_thumbnaildimensions"}}, {"model": "auth.permission", "pk": 128, "fields": {"name": "Can view thumbnail dimensions", "content_type": 33, "codename": "view_thumbnaildimensions"}}, {"model": "auth.permission", "pk": 129, "fields": {"name": "Can add text", "content_type": 34, "codename": "add_text"}}, {"model": "auth.permission", "pk": 130, "fields": {"name": "Can change text", "content_type": 34, "codename": "change_text"}}, {"model": "auth.permission", "pk": 131, "fields": {"name": "Can delete text", "content_type": 34, "codename": "delete_text"}}, {"model": "auth.permission", "pk": 132, "fields": {"name": "Can view text", "content_type": 34, "codename": "view_text"}}, {"model": "auth.permission", "pk": 133, "fields": {"name": "Can add file", "content_type": 35, "codename": "add_file"}}, {"model": "auth.permission", "pk": 134, "fields": {"name": "Can change file", "content_type": 35, "codename": "change_file"}}, {"model": "auth.permission", "pk": 135, "fields": {"name": "Can delete file", "content_type": 35, "codename": "delete_file"}}, {"model": "auth.permission", "pk": 136, "fields": {"name": "Can view file", "content_type": 35, "codename": "view_file"}}, {"model": "auth.permission", "pk": 137, "fields": {"name": "Can add folder", "content_type": 36, "codename": "add_folder"}}, {"model": "auth.permission", "pk": 138, "fields": {"name": "Can change folder", "content_type": 36, "codename": "change_folder"}}, {"model": "auth.permission", "pk": 139, "fields": {"name": "Can delete folder", "content_type": 36, "codename": "delete_folder"}}, {"model": "auth.permission", "pk": 140, "fields": {"name": "Can view folder", "content_type": 36, "codename": "view_folder"}}, {"model": "auth.permission", "pk": 141, "fields": {"name": "Can add icon", "content_type": 37, "codename": "add_icon"}}, {"model": "auth.permission", "pk": 142, "fields": {"name": "Can change icon", "content_type": 37, "codename": "change_icon"}}, {"model": "auth.permission", "pk": 143, "fields": {"name": "Can delete icon", "content_type": 37, "codename": "delete_icon"}}, {"model": "auth.permission", "pk": 144, "fields": {"name": "Can view icon", "content_type": 37, "codename": "view_icon"}}, {"model": "auth.permission", "pk": 145, "fields": {"name": "Can add link", "content_type": 38, "codename": "add_link"}}, {"model": "auth.permission", "pk": 146, "fields": {"name": "Can change link", "content_type": 38, "codename": "change_link"}}, {"model": "auth.permission", "pk": 147, "fields": {"name": "Can delete link", "content_type": 38, "codename": "delete_link"}}, {"model": "auth.permission", "pk": 148, "fields": {"name": "Can view link", "content_type": 38, "codename": "view_link"}}, {"model": "auth.permission", "pk": 149, "fields": {"name": "Can add picture", "content_type": 39, "codename": "add_picture"}}, {"model": "auth.permission", "pk": 150, "fields": {"name": "Can change picture", "content_type": 39, "codename": "change_picture"}}, {"model": "auth.permission", "pk": 151, "fields": {"name": "Can delete picture", "content_type": 39, "codename": "delete_picture"}}, {"model": "auth.permission", "pk": 152, "fields": {"name": "Can view picture", "content_type": 39, "codename": "view_picture"}}, {"model": "auth.permission", "pk": 153, "fields": {"name": "Can add style", "content_type": 40, "codename": "add_style"}}, {"model": "auth.permission", "pk": 154, "fields": {"name": "Can change style", "content_type": 40, "codename": "change_style"}}, {"model": "auth.permission", "pk": 155, "fields": {"name": "Can delete style", "content_type": 40, "codename": "delete_style"}}, {"model": "auth.permission", "pk": 156, "fields": {"name": "Can view style", "content_type": 40, "codename": "view_style"}}, {"model": "auth.permission", "pk": 157, "fields": {"name": "Can add google map", "content_type": 41, "codename": "add_googlemap"}}, {"model": "auth.permission", "pk": 158, "fields": {"name": "Can change google map", "content_type": 41, "codename": "change_googlemap"}}, {"model": "auth.permission", "pk": 159, "fields": {"name": "Can delete google map", "content_type": 41, "codename": "delete_googlemap"}}, {"model": "auth.permission", "pk": 160, "fields": {"name": "Can view google map", "content_type": 41, "codename": "view_googlemap"}}, {"model": "auth.permission", "pk": 161, "fields": {"name": "Can add google map marker", "content_type": 42, "codename": "add_googlemapmarker"}}, {"model": "auth.permission", "pk": 162, "fields": {"name": "Can change google map marker", "content_type": 42, "codename": "change_googlemapmarker"}}, {"model": "auth.permission", "pk": 163, "fields": {"name": "Can delete google map marker", "content_type": 42, "codename": "delete_googlemapmarker"}}, {"model": "auth.permission", "pk": 164, "fields": {"name": "Can view google map marker", "content_type": 42, "codename": "view_googlemapmarker"}}, {"model": "auth.permission", "pk": 165, "fields": {"name": "Can add google map route", "content_type": 43, "codename": "add_googlemaproute"}}, {"model": "auth.permission", "pk": 166, "fields": {"name": "Can change google map route", "content_type": 43, "codename": "change_googlemaproute"}}, {"model": "auth.permission", "pk": 167, "fields": {"name": "Can delete google map route", "content_type": 43, "codename": "delete_googlemaproute"}}, {"model": "auth.permission", "pk": 168, "fields": {"name": "Can view google map route", "content_type": 43, "codename": "view_googlemaproute"}}, {"model": "auth.permission", "pk": 169, "fields": {"name": "Can add video player", "content_type": 44, "codename": "add_videoplayer"}}, {"model": "auth.permission", "pk": 170, "fields": {"name": "Can change video player", "content_type": 44, "codename": "change_videoplayer"}}, {"model": "auth.permission", "pk": 171, "fields": {"name": "Can delete video player", "content_type": 44, "codename": "delete_videoplayer"}}, {"model": "auth.permission", "pk": 172, "fields": {"name": "Can view video player", "content_type": 44, "codename": "view_videoplayer"}}, {"model": "auth.permission", "pk": 173, "fields": {"name": "Can add video source", "content_type": 45, "codename": "add_videosource"}}, {"model": "auth.permission", "pk": 174, "fields": {"name": "Can change video source", "content_type": 45, "codename": "change_videosource"}}, {"model": "auth.permission", "pk": 175, "fields": {"name": "Can delete video source", "content_type": 45, "codename": "delete_videosource"}}, {"model": "auth.permission", "pk": 176, "fields": {"name": "Can view video source", "content_type": 45, "codename": "view_videosource"}}, {"model": "auth.permission", "pk": 177, "fields": {"name": "Can add video track", "content_type": 46, "codename": "add_videotrack"}}, {"model": "auth.permission", "pk": 178, "fields": {"name": "Can change video track", "content_type": 46, "codename": "change_videotrack"}}, {"model": "auth.permission", "pk": 179, "fields": {"name": "Can delete video track", "content_type": 46, "codename": "delete_videotrack"}}, {"model": "auth.permission", "pk": 180, "fields": {"name": "Can view video track", "content_type": 46, "codename": "view_videotrack"}}, {"model": "auth.permission", "pk": 181, "fields": {"name": "Can add bootstrap4 alerts", "content_type": 47, "codename": "add_bootstrap4alerts"}}, {"model": "auth.permission", "pk": 182, "fields": {"name": "Can change bootstrap4 alerts", "content_type": 47, "codename": "change_bootstrap4alerts"}}, {"model": "auth.permission", "pk": 183, "fields": {"name": "Can delete bootstrap4 alerts", "content_type": 47, "codename": "delete_bootstrap4alerts"}}, {"model": "auth.permission", "pk": 184, "fields": {"name": "Can view bootstrap4 alerts", "content_type": 47, "codename": "view_bootstrap4alerts"}}, {"model": "auth.permission", "pk": 185, "fields": {"name": "Can add bootstrap4 badge", "content_type": 48, "codename": "add_bootstrap4badge"}}, {"model": "auth.permission", "pk": 186, "fields": {"name": "Can change bootstrap4 badge", "content_type": 48, "codename": "change_bootstrap4badge"}}, {"model": "auth.permission", "pk": 187, "fields": {"name": "Can delete bootstrap4 badge", "content_type": 48, "codename": "delete_bootstrap4badge"}}, {"model": "auth.permission", "pk": 188, "fields": {"name": "Can view bootstrap4 badge", "content_type": 48, "codename": "view_bootstrap4badge"}}, {"model": "auth.permission", "pk": 189, "fields": {"name": "Can add bootstrap4 card", "content_type": 49, "codename": "add_bootstrap4card"}}, {"model": "auth.permission", "pk": 190, "fields": {"name": "Can change bootstrap4 card", "content_type": 49, "codename": "change_bootstrap4card"}}, {"model": "auth.permission", "pk": 191, "fields": {"name": "Can delete bootstrap4 card", "content_type": 49, "codename": "delete_bootstrap4card"}}, {"model": "auth.permission", "pk": 192, "fields": {"name": "Can view bootstrap4 card", "content_type": 49, "codename": "view_bootstrap4card"}}, {"model": "auth.permission", "pk": 193, "fields": {"name": "Can add bootstrap4 card inner", "content_type": 50, "codename": "add_bootstrap4cardinner"}}, {"model": "auth.permission", "pk": 194, "fields": {"name": "Can change bootstrap4 card inner", "content_type": 50, "codename": "change_bootstrap4cardinner"}}, {"model": "auth.permission", "pk": 195, "fields": {"name": "Can delete bootstrap4 card inner", "content_type": 50, "codename": "delete_bootstrap4cardinner"}}, {"model": "auth.permission", "pk": 196, "fields": {"name": "Can view bootstrap4 card inner", "content_type": 50, "codename": "view_bootstrap4cardinner"}}, {"model": "auth.permission", "pk": 197, "fields": {"name": "Can add bootstrap4 carousel", "content_type": 51, "codename": "add_bootstrap4carousel"}}, {"model": "auth.permission", "pk": 198, "fields": {"name": "Can change bootstrap4 carousel", "content_type": 51, "codename": "change_bootstrap4carousel"}}, {"model": "auth.permission", "pk": 199, "fields": {"name": "Can delete bootstrap4 carousel", "content_type": 51, "codename": "delete_bootstrap4carousel"}}, {"model": "auth.permission", "pk": 200, "fields": {"name": "Can view bootstrap4 carousel", "content_type": 51, "codename": "view_bootstrap4carousel"}}, {"model": "auth.permission", "pk": 201, "fields": {"name": "Can add bootstrap4 carousel slide", "content_type": 52, "codename": "add_bootstrap4carouselslide"}}, {"model": "auth.permission", "pk": 202, "fields": {"name": "Can change bootstrap4 carousel slide", "content_type": 52, "codename": "change_bootstrap4carouselslide"}}, {"model": "auth.permission", "pk": 203, "fields": {"name": "Can delete bootstrap4 carousel slide", "content_type": 52, "codename": "delete_bootstrap4carouselslide"}}, {"model": "auth.permission", "pk": 204, "fields": {"name": "Can view bootstrap4 carousel slide", "content_type": 52, "codename": "view_bootstrap4carouselslide"}}, {"model": "auth.permission", "pk": 205, "fields": {"name": "Can add bootstrap4 collapse", "content_type": 53, "codename": "add_bootstrap4collapse"}}, {"model": "auth.permission", "pk": 206, "fields": {"name": "Can change bootstrap4 collapse", "content_type": 53, "codename": "change_bootstrap4collapse"}}, {"model": "auth.permission", "pk": 207, "fields": {"name": "Can delete bootstrap4 collapse", "content_type": 53, "codename": "delete_bootstrap4collapse"}}, {"model": "auth.permission", "pk": 208, "fields": {"name": "Can view bootstrap4 collapse", "content_type": 53, "codename": "view_bootstrap4collapse"}}, {"model": "auth.permission", "pk": 209, "fields": {"name": "Can add bootstrap4 collapse container", "content_type": 54, "codename": "add_bootstrap4collapsecontainer"}}, {"model": "auth.permission", "pk": 210, "fields": {"name": "Can change bootstrap4 collapse container", "content_type": 54, "codename": "change_bootstrap4collapsecontainer"}}, {"model": "auth.permission", "pk": 211, "fields": {"name": "Can delete bootstrap4 collapse container", "content_type": 54, "codename": "delete_bootstrap4collapsecontainer"}}, {"model": "auth.permission", "pk": 212, "fields": {"name": "Can view bootstrap4 collapse container", "content_type": 54, "codename": "view_bootstrap4collapsecontainer"}}, {"model": "auth.permission", "pk": 213, "fields": {"name": "Can add bootstrap4 collapse trigger", "content_type": 55, "codename": "add_bootstrap4collapsetrigger"}}, {"model": "auth.permission", "pk": 214, "fields": {"name": "Can change bootstrap4 collapse trigger", "content_type": 55, "codename": "change_bootstrap4collapsetrigger"}}, {"model": "auth.permission", "pk": 215, "fields": {"name": "Can delete bootstrap4 collapse trigger", "content_type": 55, "codename": "delete_bootstrap4collapsetrigger"}}, {"model": "auth.permission", "pk": 216, "fields": {"name": "Can view bootstrap4 collapse trigger", "content_type": 55, "codename": "view_bootstrap4collapsetrigger"}}, {"model": "auth.permission", "pk": 217, "fields": {"name": "Can add bootstrap4 blockquote", "content_type": 56, "codename": "add_bootstrap4blockquote"}}, {"model": "auth.permission", "pk": 218, "fields": {"name": "Can change bootstrap4 blockquote", "content_type": 56, "codename": "change_bootstrap4blockquote"}}, {"model": "auth.permission", "pk": 219, "fields": {"name": "Can delete bootstrap4 blockquote", "content_type": 56, "codename": "delete_bootstrap4blockquote"}}, {"model": "auth.permission", "pk": 220, "fields": {"name": "Can view bootstrap4 blockquote", "content_type": 56, "codename": "view_bootstrap4blockquote"}}, {"model": "auth.permission", "pk": 221, "fields": {"name": "Can add bootstrap4 code", "content_type": 57, "codename": "add_bootstrap4code"}}, {"model": "auth.permission", "pk": 222, "fields": {"name": "Can change bootstrap4 code", "content_type": 57, "codename": "change_bootstrap4code"}}, {"model": "auth.permission", "pk": 223, "fields": {"name": "Can delete bootstrap4 code", "content_type": 57, "codename": "delete_bootstrap4code"}}, {"model": "auth.permission", "pk": 224, "fields": {"name": "Can view bootstrap4 code", "content_type": 57, "codename": "view_bootstrap4code"}}, {"model": "auth.permission", "pk": 225, "fields": {"name": "Can add bootstrap4 figure", "content_type": 58, "codename": "add_bootstrap4figure"}}, {"model": "auth.permission", "pk": 226, "fields": {"name": "Can change bootstrap4 figure", "content_type": 58, "codename": "change_bootstrap4figure"}}, {"model": "auth.permission", "pk": 227, "fields": {"name": "Can delete bootstrap4 figure", "content_type": 58, "codename": "delete_bootstrap4figure"}}, {"model": "auth.permission", "pk": 228, "fields": {"name": "Can view bootstrap4 figure", "content_type": 58, "codename": "view_bootstrap4figure"}}, {"model": "auth.permission", "pk": 229, "fields": {"name": "Can add bootstrap4 grid column", "content_type": 59, "codename": "add_bootstrap4gridcolumn"}}, {"model": "auth.permission", "pk": 230, "fields": {"name": "Can change bootstrap4 grid column", "content_type": 59, "codename": "change_bootstrap4gridcolumn"}}, {"model": "auth.permission", "pk": 231, "fields": {"name": "Can delete bootstrap4 grid column", "content_type": 59, "codename": "delete_bootstrap4gridcolumn"}}, {"model": "auth.permission", "pk": 232, "fields": {"name": "Can view bootstrap4 grid column", "content_type": 59, "codename": "view_bootstrap4gridcolumn"}}, {"model": "auth.permission", "pk": 233, "fields": {"name": "Can add bootstrap4 grid container", "content_type": 60, "codename": "add_bootstrap4gridcontainer"}}, {"model": "auth.permission", "pk": 234, "fields": {"name": "Can change bootstrap4 grid container", "content_type": 60, "codename": "change_bootstrap4gridcontainer"}}, {"model": "auth.permission", "pk": 235, "fields": {"name": "Can delete bootstrap4 grid container", "content_type": 60, "codename": "delete_bootstrap4gridcontainer"}}, {"model": "auth.permission", "pk": 236, "fields": {"name": "Can view bootstrap4 grid container", "content_type": 60, "codename": "view_bootstrap4gridcontainer"}}, {"model": "auth.permission", "pk": 237, "fields": {"name": "Can add bootstrap4 grid row", "content_type": 61, "codename": "add_bootstrap4gridrow"}}, {"model": "auth.permission", "pk": 238, "fields": {"name": "Can change bootstrap4 grid row", "content_type": 61, "codename": "change_bootstrap4gridrow"}}, {"model": "auth.permission", "pk": 239, "fields": {"name": "Can delete bootstrap4 grid row", "content_type": 61, "codename": "delete_bootstrap4gridrow"}}, {"model": "auth.permission", "pk": 240, "fields": {"name": "Can view bootstrap4 grid row", "content_type": 61, "codename": "view_bootstrap4gridrow"}}, {"model": "auth.permission", "pk": 241, "fields": {"name": "Can add bootstrap4 jumbotron", "content_type": 62, "codename": "add_bootstrap4jumbotron"}}, {"model": "auth.permission", "pk": 242, "fields": {"name": "Can change bootstrap4 jumbotron", "content_type": 62, "codename": "change_bootstrap4jumbotron"}}, {"model": "auth.permission", "pk": 243, "fields": {"name": "Can delete bootstrap4 jumbotron", "content_type": 62, "codename": "delete_bootstrap4jumbotron"}}, {"model": "auth.permission", "pk": 244, "fields": {"name": "Can view bootstrap4 jumbotron", "content_type": 62, "codename": "view_bootstrap4jumbotron"}}, {"model": "auth.permission", "pk": 245, "fields": {"name": "Can add bootstrap4 link", "content_type": 63, "codename": "add_bootstrap4link"}}, {"model": "auth.permission", "pk": 246, "fields": {"name": "Can change bootstrap4 link", "content_type": 63, "codename": "change_bootstrap4link"}}, {"model": "auth.permission", "pk": 247, "fields": {"name": "Can delete bootstrap4 link", "content_type": 63, "codename": "delete_bootstrap4link"}}, {"model": "auth.permission", "pk": 248, "fields": {"name": "Can view bootstrap4 link", "content_type": 63, "codename": "view_bootstrap4link"}}, {"model": "auth.permission", "pk": 249, "fields": {"name": "Can add bootstrap4 list group", "content_type": 64, "codename": "add_bootstrap4listgroup"}}, {"model": "auth.permission", "pk": 250, "fields": {"name": "Can change bootstrap4 list group", "content_type": 64, "codename": "change_bootstrap4listgroup"}}, {"model": "auth.permission", "pk": 251, "fields": {"name": "Can delete bootstrap4 list group", "content_type": 64, "codename": "delete_bootstrap4listgroup"}}, {"model": "auth.permission", "pk": 252, "fields": {"name": "Can view bootstrap4 list group", "content_type": 64, "codename": "view_bootstrap4listgroup"}}, {"model": "auth.permission", "pk": 253, "fields": {"name": "Can add bootstrap4 list group item", "content_type": 65, "codename": "add_bootstrap4listgroupitem"}}, {"model": "auth.permission", "pk": 254, "fields": {"name": "Can change bootstrap4 list group item", "content_type": 65, "codename": "change_bootstrap4listgroupitem"}}, {"model": "auth.permission", "pk": 255, "fields": {"name": "Can delete bootstrap4 list group item", "content_type": 65, "codename": "delete_bootstrap4listgroupitem"}}, {"model": "auth.permission", "pk": 256, "fields": {"name": "Can view bootstrap4 list group item", "content_type": 65, "codename": "view_bootstrap4listgroupitem"}}, {"model": "auth.permission", "pk": 257, "fields": {"name": "Can add bootstrap4 media", "content_type": 66, "codename": "add_bootstrap4media"}}, {"model": "auth.permission", "pk": 258, "fields": {"name": "Can change bootstrap4 media", "content_type": 66, "codename": "change_bootstrap4media"}}, {"model": "auth.permission", "pk": 259, "fields": {"name": "Can delete bootstrap4 media", "content_type": 66, "codename": "delete_bootstrap4media"}}, {"model": "auth.permission", "pk": 260, "fields": {"name": "Can view bootstrap4 media", "content_type": 66, "codename": "view_bootstrap4media"}}, {"model": "auth.permission", "pk": 261, "fields": {"name": "Can add bootstrap4 media body", "content_type": 67, "codename": "add_bootstrap4mediabody"}}, {"model": "auth.permission", "pk": 262, "fields": {"name": "Can change bootstrap4 media body", "content_type": 67, "codename": "change_bootstrap4mediabody"}}, {"model": "auth.permission", "pk": 263, "fields": {"name": "Can delete bootstrap4 media body", "content_type": 67, "codename": "delete_bootstrap4mediabody"}}, {"model": "auth.permission", "pk": 264, "fields": {"name": "Can view bootstrap4 media body", "content_type": 67, "codename": "view_bootstrap4mediabody"}}, {"model": "auth.permission", "pk": 265, "fields": {"name": "Can add bootstrap4 picture", "content_type": 68, "codename": "add_bootstrap4picture"}}, {"model": "auth.permission", "pk": 266, "fields": {"name": "Can change bootstrap4 picture", "content_type": 68, "codename": "change_bootstrap4picture"}}, {"model": "auth.permission", "pk": 267, "fields": {"name": "Can delete bootstrap4 picture", "content_type": 68, "codename": "delete_bootstrap4picture"}}, {"model": "auth.permission", "pk": 268, "fields": {"name": "Can view bootstrap4 picture", "content_type": 68, "codename": "view_bootstrap4picture"}}, {"model": "auth.permission", "pk": 269, "fields": {"name": "Can add bootstrap4 tab", "content_type": 69, "codename": "add_bootstrap4tab"}}, {"model": "auth.permission", "pk": 270, "fields": {"name": "Can change bootstrap4 tab", "content_type": 69, "codename": "change_bootstrap4tab"}}, {"model": "auth.permission", "pk": 271, "fields": {"name": "Can delete bootstrap4 tab", "content_type": 69, "codename": "delete_bootstrap4tab"}}, {"model": "auth.permission", "pk": 272, "fields": {"name": "Can view bootstrap4 tab", "content_type": 69, "codename": "view_bootstrap4tab"}}, {"model": "auth.permission", "pk": 273, "fields": {"name": "Can add bootstrap4 tab item", "content_type": 70, "codename": "add_bootstrap4tabitem"}}, {"model": "auth.permission", "pk": 274, "fields": {"name": "Can change bootstrap4 tab item", "content_type": 70, "codename": "change_bootstrap4tabitem"}}, {"model": "auth.permission", "pk": 275, "fields": {"name": "Can delete bootstrap4 tab item", "content_type": 70, "codename": "delete_bootstrap4tabitem"}}, {"model": "auth.permission", "pk": 276, "fields": {"name": "Can view bootstrap4 tab item", "content_type": 70, "codename": "view_bootstrap4tabitem"}}, {"model": "auth.permission", "pk": 277, "fields": {"name": "Can add bootstrap4 spacing", "content_type": 71, "codename": "add_bootstrap4spacing"}}, {"model": "auth.permission", "pk": 278, "fields": {"name": "Can change bootstrap4 spacing", "content_type": 71, "codename": "change_bootstrap4spacing"}}, {"model": "auth.permission", "pk": 279, "fields": {"name": "Can delete bootstrap4 spacing", "content_type": 71, "codename": "delete_bootstrap4spacing"}}, {"model": "auth.permission", "pk": 280, "fields": {"name": "Can view bootstrap4 spacing", "content_type": 71, "codename": "view_bootstrap4spacing"}}, {"model": "auth.user", "pk": 1, "fields": {"password": "pbkdf2_sha256$216000$COl4r5OIzs0x$NweR1NHbNBIqmhtYoMHCFtbyxLiuNDXca0O6v6ocaww=", "last_login": "2021-10-19T05:41:03.128Z", "is_superuser": true, "username": "franta", "first_name": "", "last_name": "", "email": "franta@gmail.com", "is_staff": true, "is_active": true, "date_joined": "2021-10-19T05:27:53.325Z", "groups": [], "user_permissions": []}}, {"model": "auth.user", "pk": 2, "fields": {"password": "pbkdf2_sha256$216000$mNyYejlnFIIu$XQHkH8Giyy5h09IylxyUmqHqp/mg1x6cSAQUJ2BwnQg=", "last_login": "2021-10-19T09:41:15.577Z", "is_superuser": true, "username": "student", "first_name": "", "last_name": "", "email": "axareen44@gmail.com", "is_staff": true, "is_active": true, "date_joined": "2021-10-19T09:28:46.237Z", "groups": [], "user_permissions": []}}, {"model": "auth.user", "pk": 3, "fields": {"password": "pbkdf2_sha256$216000$FgEG1khRDK8y$rxSUwi9MZsThuuIShqQQCY1RzHjojAUtISTSonF8WhE=", "last_login": "2021-11-08T12:34:21.633Z", "is_superuser": true, "username": "user", "first_name": "", "last_name": "", "email": "", "is_staff": true, "is_active": true, "date_joined": "2021-11-08T12:33:48.582Z", "groups": [], "user_permissions": []}}, {"model": "contenttypes.contenttype", "pk": 1, "fields": {"app_label": "cms", "model": "placeholder"}}, {"model": "contenttypes.contenttype", "pk": 2, "fields": {"app_label": "cms", "model": "page"}}, {"model": "contenttypes.contenttype", "pk": 3, "fields": {"app_label": "admin", "model": "logentry"}}, {"model": "contenttypes.contenttype", "pk": 4, "fields": {"app_label": "auth", "model": "permission"}}, {"model": "contenttypes.contenttype", "pk": 5, "fields": {"app_label": "auth", "model": "group"}}, {"model": "contenttypes.contenttype", "pk": 6, "fields": {"app_label": "auth", "model": "user"}}, {"model": "contenttypes.contenttype", "pk": 7, "fields": {"app_label": "contenttypes", "model": "contenttype"}}, {"model": "contenttypes.contenttype", "pk": 8, "fields": {"app_label": "sessions", "model": "session"}}, {"model": "contenttypes.contenttype", "pk": 9, "fields": {"app_label": "sites", "model": "site"}}, {"model": "contenttypes.contenttype", "pk": 10, "fields": {"app_label": "cms", "model": "cmsplugin"}}, {"model": "contenttypes.contenttype", "pk": 11, "fields": {"app_label": "cms", "model": "aliaspluginmodel"}}, {"model": "contenttypes.contenttype", "pk": 12, "fields": {"app_label": "cms", "model": "globalpagepermission"}}, {"model": "contenttypes.contenttype", "pk": 13, "fields": {"app_label": "cms", "model": "pagepermission"}}, {"model": "contenttypes.contenttype", "pk": 14, "fields": {"app_label": "cms", "model": "pageuser"}}, {"model": "contenttypes.contenttype", "pk": 15, "fields": {"app_label": "cms", "model": "pageusergroup"}}, {"model": "contenttypes.contenttype", "pk": 16, "fields": {"app_label": "cms", "model": "placeholderreference"}}, {"model": "contenttypes.contenttype", "pk": 17, "fields": {"app_label": "cms", "model": "staticplaceholder"}}, {"model": "contenttypes.contenttype", "pk": 18, "fields": {"app_label": "cms", "model": "title"}}, {"model": "contenttypes.contenttype", "pk": 19, "fields": {"app_label": "cms", "model": "usersettings"}}, {"model": "contenttypes.contenttype", "pk": 20, "fields": {"app_label": "cms", "model": "urlconfrevision"}}, {"model": "contenttypes.contenttype", "pk": 21, "fields": {"app_label": "cms", "model": "pagetype"}}, {"model": "contenttypes.contenttype", "pk": 22, "fields": {"app_label": "cms", "model": "treenode"}}, {"model": "contenttypes.contenttype", "pk": 23, "fields": {"app_label": "menus", "model": "cachekey"}}, {"model": "contenttypes.contenttype", "pk": 24, "fields": {"app_label": "filer", "model": "clipboard"}}, {"model": "contenttypes.contenttype", "pk": 25, "fields": {"app_label": "filer", "model": "clipboarditem"}}, {"model": "contenttypes.contenttype", "pk": 26, "fields": {"app_label": "filer", "model": "file"}}, {"model": "contenttypes.contenttype", "pk": 27, "fields": {"app_label": "filer", "model": "folder"}}, {"model": "contenttypes.contenttype", "pk": 28, "fields": {"app_label": "filer", "model": "folderpermission"}}, {"model": "contenttypes.contenttype", "pk": 29, "fields": {"app_label": "filer", "model": "image"}}, {"model": "contenttypes.contenttype", "pk": 30, "fields": {"app_label": "filer", "model": "thumbnailoption"}}, {"model": "contenttypes.contenttype", "pk": 31, "fields": {"app_label": "easy_thumbnails", "model": "source"}}, {"model": "contenttypes.contenttype", "pk": 32, "fields": {"app_label": "easy_thumbnails", "model": "thumbnail"}}, {"model": "contenttypes.contenttype", "pk": 33, "fields": {"app_label": "easy_thumbnails", "model": "thumbnaildimensions"}}, {"model": "contenttypes.contenttype", "pk": 34, "fields": {"app_label": "djangocms_text_ckeditor", "model": "text"}}, {"model": "contenttypes.contenttype", "pk": 35, "fields": {"app_label": "djangocms_file", "model": "file"}}, {"model": "contenttypes.contenttype", "pk": 36, "fields": {"app_label": "djangocms_file", "model": "folder"}}, {"model": "contenttypes.contenttype", "pk": 37, "fields": {"app_label": "djangocms_icon", "model": "icon"}}, {"model": "contenttypes.contenttype", "pk": 38, "fields": {"app_label": "djangocms_link", "model": "link"}}, {"model": "contenttypes.contenttype", "pk": 39, "fields": {"app_label": "djangocms_picture", "model": "picture"}}, {"model": "contenttypes.contenttype", "pk": 40, "fields": {"app_label": "djangocms_style", "model": "style"}}, {"model": "contenttypes.contenttype", "pk": 41, "fields": {"app_label": "djangocms_googlemap", "model": "googlemap"}}, {"model": "contenttypes.contenttype", "pk": 42, "fields": {"app_label": "djangocms_googlemap", "model": "googlemapmarker"}}, {"model": "contenttypes.contenttype", "pk": 43, "fields": {"app_label": "djangocms_googlemap", "model": "googlemaproute"}}, {"model": "contenttypes.contenttype", "pk": 44, "fields": {"app_label": "djangocms_video", "model": "videoplayer"}}, {"model": "contenttypes.contenttype", "pk": 45, "fields": {"app_label": "djangocms_video", "model": "videosource"}}, {"model": "contenttypes.contenttype", "pk": 46, "fields": {"app_label": "djangocms_video", "model": "videotrack"}}, {"model": "contenttypes.contenttype", "pk": 47, "fields": {"app_label": "bootstrap4_alerts", "model": "bootstrap4alerts"}}, {"model": "contenttypes.contenttype", "pk": 48, "fields": {"app_label": "bootstrap4_badge", "model": "bootstrap4badge"}}, {"model": "contenttypes.contenttype", "pk": 49, "fields": {"app_label": "bootstrap4_card", "model": "bootstrap4card"}}, {"model": "contenttypes.contenttype", "pk": 50, "fields": {"app_label": "bootstrap4_card", "model": "bootstrap4cardinner"}}, {"model": "contenttypes.contenttype", "pk": 51, "fields": {"app_label": "bootstrap4_carousel", "model": "bootstrap4carousel"}}, {"model": "contenttypes.contenttype", "pk": 52, "fields": {"app_label": "bootstrap4_carousel", "model": "bootstrap4carouselslide"}}, {"model": "contenttypes.contenttype", "pk": 53, "fields": {"app_label": "bootstrap4_collapse", "model": "bootstrap4collapse"}}, {"model": "contenttypes.contenttype", "pk": 54, "fields": {"app_label": "bootstrap4_collapse", "model": "bootstrap4collapsecontainer"}}, {"model": "contenttypes.contenttype", "pk": 55, "fields": {"app_label": "bootstrap4_collapse", "model": "bootstrap4collapsetrigger"}}, {"model": "contenttypes.contenttype", "pk": 56, "fields": {"app_label": "bootstrap4_content", "model": "bootstrap4blockquote"}}, {"model": "contenttypes.contenttype", "pk": 57, "fields": {"app_label": "bootstrap4_content", "model": "bootstrap4code"}}, {"model": "contenttypes.contenttype", "pk": 58, "fields": {"app_label": "bootstrap4_content", "model": "bootstrap4figure"}}, {"model": "contenttypes.contenttype", "pk": 59, "fields": {"app_label": "bootstrap4_grid", "model": "bootstrap4gridcolumn"}}, {"model": "contenttypes.contenttype", "pk": 60, "fields": {"app_label": "bootstrap4_grid", "model": "bootstrap4gridcontainer"}}, {"model": "contenttypes.contenttype", "pk": 61, "fields": {"app_label": "bootstrap4_grid", "model": "bootstrap4gridrow"}}, {"model": "contenttypes.contenttype", "pk": 62, "fields": {"app_label": "bootstrap4_jumbotron", "model": "bootstrap4jumbotron"}}, {"model": "contenttypes.contenttype", "pk": 63, "fields": {"app_label": "bootstrap4_link", "model": "bootstrap4link"}}, {"model": "contenttypes.contenttype", "pk": 64, "fields": {"app_label": "bootstrap4_listgroup", "model": "bootstrap4listgroup"}}, {"model": "contenttypes.contenttype", "pk": 65, "fields": {"app_label": "bootstrap4_listgroup", "model": "bootstrap4listgroupitem"}}, {"model": "contenttypes.contenttype", "pk": 66, "fields": {"app_label": "bootstrap4_media", "model": "bootstrap4media"}}, {"model": "contenttypes.contenttype", "pk": 67, "fields": {"app_label": "bootstrap4_media", "model": "bootstrap4mediabody"}}, {"model": "contenttypes.contenttype", "pk": 68, "fields": {"app_label": "bootstrap4_picture", "model": "bootstrap4picture"}}, {"model": "contenttypes.contenttype", "pk": 69, "fields": {"app_label": "bootstrap4_tabs", "model": "bootstrap4tab"}}, {"model": "contenttypes.contenttype", "pk": 70, "fields": {"app_label": "bootstrap4_tabs", "model": "bootstrap4tabitem"}}, {"model": "contenttypes.contenttype", "pk": 71, "fields": {"app_label": "bootstrap4_utilities", "model": "bootstrap4spacing"}}, {"model": "sessions.session", "pk": "d9b7wnxl2mcbpqu2134gkgo13a6w95g2", "fields": {"session_data": ".eJxVTstuwyAQ_BfOlWUwjiHH3vMNaGHXNa1rIsBNlcj_HiyjqD3tzmNn58EMrHkya6JoPLIz69jbX86C-6JlF_ATlo_QuLDk6G2zW5qqpuYSkOb36v0XMEGayrVVYHveu14Jwdte2U4OAqGTKE9COa1bPXR21LbVnEC2OHCuxQlBdpYrDiXUfSeTQ5gtRIM-gZ2p9BphTnSIhD6zc45rxddIP55uL8_N3yGiqcNFgkzmcDxYynQtPdvyaF8NQobCbxWOfqZ0YPrNEV76tj0BQeduZQ:1mk3qw:VkBe8sw-reA2MLVJv3rN8zvT76RIsbus6g7bLeZjRsI", "expire_date": "2021-11-22T12:34:22.023Z"}}, {"model": "sessions.session", "pk": "f0t9zqgxwks06pcb2dyfmdpwhuxor0kx", "fields": {"session_data": ".eJxVjtFuwyAMRf-F5yqCwpqsj3vvNyCDTcPGQgVkrVrl30sUVHVP9vW5vvaDaZjLqOdMSXtkRybY7n1mwP7QtAL8hukcOxunkrzpVkvXaO5OESl8Ne-_gBHyWLctAipr0NHAD3IvnVVCGjlwpQTneyekcp-iP8AwSP7hqO-tU0ZIi31FxtRQ-5t1iTEYSBp9BhOo_uUgZNogoS_sWNLc9CXRn6fry3P1d0ioW7GJoJDeHA-WC13qn7weWluNUKDOlyadD5Q3TbeS4MWX5Qn3EG9K:1mciRJ:VWZrQDJwG6SU9neKu15RC-iVPYZt9mHfsqzXDXRHCuo", "expire_date": "2021-11-02T06:17:33.848Z"}}, {"model": "sessions.session", "pk": "kotd23yvuzogu0me9i00dqf3r0zzstah", "fields": {"session_data": ".eJxVTttuwyAM_Reep4gk1En7uPd-AzLGLGxZqICs06r8-4iCqu3JPhcfn4fQuOZJr4mj9lZcRCde_nIG6YOXXbDvuLyFhsKSozfNbmmqmpprsDy_Vu-_gAnTVK6ZLBH1I4BU0LeDgvZMAGDa4Sx5lAhGOTLghlPH0p166gAVAikz9j3sofSZdA5hNhi19QnNzKWXwznxIbL1WVxyXCu-Rf7yfH967v4Ho9V1UGTMrA_HQ6TMt9JTlkf7qi1mLPxWofMzpwPzd4741LftF9u_bzU:1md9VX:ea8uBFCGH5cpBwvO5B3Z5yil3gSqAn5T6B0EINg-_Dw", "expire_date": "2021-11-03T11:11:43.137Z"}}, {"model": "sites.site", "pk": 1, "fields": {"domain": "example.com", "name": "example.com"}}, {"model": "cms.usersettings", "pk": 1, "fields": {"user": 1, "language": "en", "clipboard": 1}}, {"model": "cms.usersettings", "pk": 2, "fields": {"user": 2, "language": "en", "clipboard": 2}}, {"model": "cms.usersettings", "pk": 3, "fields": {"user": 3, "language": "en", "clipboard": 3}}, {"model": "cms.placeholder", "pk": 1, "fields": {"slot": "clipboard", "default_width": null}}, {"model": "cms.placeholder", "pk": 2, "fields": {"slot": "clipboard", "default_width": null}}, {"model": "cms.placeholder", "pk": 3, "fields": {"slot": "clipboard", "default_width": null}}]